elysia/__init__.py
elysia/__metadata__.py
elysia/config.py
elysia/objects.py
elysia/api/__init__.py
elysia/api/api_types.py
elysia/api/app.py
elysia/api/cli.py
elysia/api/custom_tools.py
elysia/api/core/__init__.py
elysia/api/core/log.py
elysia/api/dependencies/__init__.py
elysia/api/dependencies/common.py
elysia/api/middleware/__init__.py
elysia/api/middleware/error_handlers.py
elysia/api/routes/__init__.py
elysia/api/routes/collections.py
elysia/api/routes/db.py
elysia/api/routes/feedback.py
elysia/api/routes/init.py
elysia/api/routes/processor.py
elysia/api/routes/query.py
elysia/api/routes/tools.py
elysia/api/routes/tree_config.py
elysia/api/routes/user_config.py
elysia/api/routes/utils.py
elysia/api/services/__init__.py
elysia/api/services/tree.py
elysia/api/services/user.py
elysia/api/static/404.html
elysia/api/static/icon.svg
elysia/api/static/index.html
elysia/api/static/index.txt
elysia/api/static/logo.svg
elysia/api/static/weaviate-logo.svg
elysia/api/static/_next/static/chunks/0e762574-c759a1561c192a17.js
elysia/api/static/_next/static/chunks/117-25e58301f848c60f.js
elysia/api/static/_next/static/chunks/1a258343-150c78f4297d2358.js
elysia/api/static/_next/static/chunks/30a37ab2-322b0b940673459b.js
elysia/api/static/_next/static/chunks/349-1022b66d793b606a.js
elysia/api/static/_next/static/chunks/385cb88d-8bfdadb8caecc2fb.js
elysia/api/static/_next/static/chunks/455.7a2f31b70b175710.js
elysia/api/static/_next/static/chunks/479ba886-f85ef559edbf188b.js
elysia/api/static/_next/static/chunks/52ab8b6c-668757d47a6e6fc6.js
elysia/api/static/_next/static/chunks/53c13509-fcf4cae42fb19e2e.js
elysia/api/static/_next/static/chunks/59650de3-4892ddf82b39e2a7.js
elysia/api/static/_next/static/chunks/5e22fd23-dcf8510321a066a0.js
elysia/api/static/_next/static/chunks/656-1c41fa57e3c53c77.js
elysia/api/static/_next/static/chunks/695-196e1d8b26f70535.js
elysia/api/static/_next/static/chunks/748.3b9d198cc4056057.js
elysia_ai-0.2.7.dist-info/METADATA
elysia_ai-0.2.7.dist-info/WHEEL
elysia_ai-0.2.7.dist-info/entry_points.txt
elysia_ai-0.2.7.dist-info/licenses/LICENSE
elysia_ai-0.2.7.dist-info/RECORD
