Metadata-Version: 2.4
Name: elysia-ai
Version: 0.2.7
Summary: Elysia is an open-source agentic platform for searching data. It is built with customisation in mind, allowing you to build agents and tools that are tailored to your specific use case. It uses Weaviate as the default retrieval tools, and can interface with your data stored in a Weaviate cluster.
Project-URL: Homepage, https://elysia.weaviate.io
Project-URL: Documentation, https://weaviate.github.io/elysia/
Author-email: Danny <danny@weaviate.io>
License-File: LICENSE
Keywords: agentic,ai,llm,retrieval,search,weaviate
Classifier: Development Status :: 4 - Beta
Requires-Python: <3.13.0,>=3.10.0
Requires-Dist: apscheduler==3.11.0
Requires-Dist: bcrypt>=4.3.0
Requires-Dist: blis<1.3.0,>=1.2.0
Requires-Dist: cryptography>=44.0.3
Requires-Dist: dspy-ai>=3.0.0
Requires-Dist: fastapi[standard]>=0.115.11
Requires-Dist: httpx==0.28.1
Requires-Dist: litellm<1.76.0,>=1.74.15
Requires-Dist: matplotlib>=3.10.3
Requires-Dist: nest-asyncio==1.6.0
Requires-Dist: pip>=25.2
Requires-Dist: psutil==7.0.0
Requires-Dist: pympler==1.1
Requires-Dist: python-multipart==0.0.18
Requires-Dist: rich<=14.0.0,>=13.7.1
Requires-Dist: spacy==3.8.7
Requires-Dist: thinc<8.4.0,>=8.3.4
Requires-Dist: uvicorn[standard]==0.35.0
Requires-Dist: weaviate-client>=4.16.7
Provides-Extra: dev
Requires-Dist: accelerate==1.5.2; extra == 'dev'
Requires-Dist: cairosvg==2.7.1; extra == 'dev'
Requires-Dist: deepeval>=3.2.6; extra == 'dev'
Requires-Dist: mkdocs-material[imaging]==9.6.12; extra == 'dev'
Requires-Dist: mkdocstrings[python]==0.29.1; extra == 'dev'
Requires-Dist: pillow==10.4.0; extra == 'dev'
Requires-Dist: pytest-asyncio>=0.21.2; extra == 'dev'
Requires-Dist: pytest-cov>=6.2.1; extra == 'dev'
Requires-Dist: pytest>=7.4.4; extra == 'dev'
Requires-Dist: setuptools==78.1.0; extra == 'dev'
Requires-Dist: websocket-client==1.8.0; extra == 'dev'
